snappy/__init__.py
snappy/datapacks.py
snappy/htmlMagic.py
snappy/main.py
snappy_Labfox-0.1.1.dist-info/LICENSE
snappy_Labfox-0.1.1.dist-info/METADATA
snappy_Labfox-0.1.1.dist-info/WHEEL
snappy_Labfox-0.1.1.dist-info/top_level.txt
snappy_Labfox-0.1.1.dist-info/RECORD
