Metadata-Version: 2.1
Name: snappy_Labfox
Version: 0.1.1
Summary: An snapchat api
Author-email: Labfox <consockbind@gmail.com>
Project-URL: Homepage, https://github.com/Labfox/snappy
Project-URL: Issues, https://github.com/Labfox/snappy/issues
Classifier: Programming Language :: Python :: 3
Classifier: License :: OSI Approved :: MIT License
Classifier: Operating System :: OS Independent
Requires-Python: >=3.11
License-File: LICENSE
Requires-Dist: selenium
Requires-Dist: beautifulsoup4
Requires-Dist: requests
